fieldconfig/__init__.py
fieldconfig/config.py
fieldconfig/field.py
fieldconfig-0.1.6.dist-info/METADATA
fieldconfig-0.1.6.dist-info/WHEEL
fieldconfig-0.1.6.dist-info/RECORD
