Metadata-Version: 2.1
Name: fieldconfig
Version: 0.1.6
Summary: FieldConfig is a configuration management library for Python.
Home-page: https://github.com/marcel-dehaan/fieldconfig
License: Apache-2.0
Author: Marcel de Haan
Author-email: mdehaan35@gmail.com
Requires-Python: >=3.7,<4.0
Classifier: Development Status :: 3 - Alpha
Classifier: Intended Audience :: Developers
Classifier: License :: OSI Approved :: Apache Software License
Classifier: Programming Language :: Python :: 3
Classifier: Programming Language :: Python :: 3.7
Classifier: Programming Language :: Python :: 3.8
Classifier: Programming Language :: Python :: 3.9
Classifier: Programming Language :: Python :: 3.10
Classifier: Programming Language :: Python :: 3.11
Classifier: Programming Language :: Python :: 3.12
Classifier: Topic :: Software Development
Requires-Dist: PyYAML
